README.md
setup.py
py_nifty_cloud/__init__.py
py_nifty_cloud/nifty_cloud_request.py
py_nifty_cloud.egg-info/PKG-INFO
py_nifty_cloud.egg-info/SOURCES.txt
py_nifty_cloud.egg-info/dependency_links.txt
py_nifty_cloud.egg-info/not-zip-safe
py_nifty_cloud.egg-info/requires.txt
py_nifty_cloud.egg-info/top_level.txt