Metadata-Version: 1.1
Name: py-nifty-cloud
Version: 0.9.5
Summary: wrapper for request to Nifty Cloud mobile backend
Home-page: https://github.com/petitviolet/py_nifty_cloud
Author: petitviolet
Author-email: violethero0820@gmail.com
License: MIT
Platform: Mac OS X
Classifier: Environment :: Web Environment
Classifier: Intended Audience :: Developers
Classifier: Operating System :: OS Independent
Classifier: Programming Language :: Python
Classifier: Topic :: Software Development
